cloudreg/__init__.py
cloudreg/scripts/__init__.py
cloudreg/scripts/colm_pipeline.py
cloudreg/scripts/correct_raw_data.py
cloudreg/scripts/correct_stitched_data.py
cloudreg/scripts/create_precomputed_volume.py
cloudreg/scripts/create_precomputed_volumes.py
cloudreg/scripts/download_data.py
cloudreg/scripts/download_raw_data.py
cloudreg/scripts/downsample_iso.py
cloudreg/scripts/ingest_image_stack.py
cloudreg/scripts/paraconverter.py
cloudreg/scripts/parastitcher.py
cloudreg/scripts/quantify_fluorescence_by_region.py
cloudreg/scripts/registration.py
cloudreg/scripts/registration_accuracy.py
cloudreg/scripts/run_colm_pipeline_ec2.py
cloudreg/scripts/run_registration_ec2.py
cloudreg/scripts/run_registration_local.py
cloudreg/scripts/scratch.py
cloudreg/scripts/segment_axons.py
cloudreg/scripts/stitching.py
cloudreg/scripts/transform_data.py
cloudreg/scripts/transform_points.py
cloudreg/scripts/util.py
cloudreg/scripts/visualization.py
CloudReg-1.0.post2.dist-info/LICENSE
CloudReg-1.0.post2.dist-info/METADATA
CloudReg-1.0.post2.dist-info/WHEEL
CloudReg-1.0.post2.dist-info/top_level.txt
CloudReg-1.0.post2.dist-info/RECORD
