Metadata-Version: 2.1
Name: CloudReg
Version: 1.0.post2
Summary: Automatic terabyte-scale cross-modal brain volume registration
Home-page: https://github.com/neurodata/CloudReg
Author: ('Vikram Chandrashekhar, Daniel Tward',)
License: Apache License 2.0
Classifier: Development Status :: 3 - Alpha
Classifier: Intended Audience :: Science/Research
Classifier: Topic :: Scientific/Engineering :: Mathematics
Classifier: License :: OSI Approved :: Apache Software License
Classifier: Programming Language :: Python :: 3
Classifier: Programming Language :: Python :: 3.5
Classifier: Programming Language :: Python :: 3.6
Classifier: Programming Language :: Python :: 3.7
License-File: LICENSE
Requires-Dist: paramiko
Requires-Dist: joblib
Requires-Dist: SimpleITK (>=2.0.0)
Requires-Dist: boto3
Requires-Dist: tqdm
Requires-Dist: awscli
Requires-Dist: cloud-volume
Requires-Dist: h5py
Requires-Dist: scipy
Requires-Dist: tinybrain
Requires-Dist: tifffile
Requires-Dist: imagecodecs
